gval/__init__.py
gval/accessors/__init__.py
gval/accessors/gval_array.py
gval/accessors/gval_dataframe.py
gval/accessors/gval_dataset.py
gval/accessors/gval_xarray.py
gval/attributes/attributes.py
gval/catalogs/catalogs.py
gval/comparison/__init__.py
gval/comparison/agreement.py
gval/comparison/compute_categorical_metrics.py
gval/comparison/compute_comparison.py
gval/comparison/compute_continuous_metrics.py
gval/comparison/compute_probabilistic_metrics.py
gval/comparison/pairing_functions.py
gval/comparison/tabulation.py
gval/homogenize/__init__.py
gval/homogenize/numeric_alignment.py
gval/homogenize/rasterize.py
gval/homogenize/spatial_alignment.py
gval/homogenize/vectorize.py
gval/statistics/__init__.py
gval/statistics/base_statistics.py
gval/statistics/categorical_stat_funcs.py
gval/statistics/categorical_statistics.py
gval/statistics/continuous_stat_funcs.py
gval/statistics/continuous_stat_utils.py
gval/statistics/continuous_statistics.py
gval/statistics/test.py
gval/statistics/test2.py
gval/statistics/test3.py
gval/statistics/test4.py
gval/subsampling/__init__.py
gval/subsampling/subsampling.py
gval/utils/__init__.py
gval/utils/exceptions.py
gval/utils/loading_datasets.py
gval/utils/schemas.py
gval/utils/visualize.py
gval-0.2.11.dist-info/licenses/LICENSE.MD
gval-0.2.11.dist-info/METADATA
gval-0.2.11.dist-info/WHEEL
gval-0.2.11.dist-info/top_level.txt
gval-0.2.11.dist-info/RECORD
