Metadata-Version: 2.4
Name: gval
Version: 0.2.11
Summary: Flexible, portable, and efficient geospatial evaluations for a variety of data.
Author-email: Fernando Aristizabal <fernando.aristizabal@noaa.gov>, Gregory Petrochenkov <gregory.petrochenkov@noaa.gov>
License: MIT
Project-URL: Repository, https://github.com/NOAA-OWP/gval
Project-URL: Homepage, https://noaa-owp.github.io/gval/
Keywords: geospatial,evaluations
Requires-Python: >=3.9
License-File: LICENSE.MD
Requires-Dist: rioxarray>=0.13.4
Requires-Dist: dask<2025,>=2023.5.0
Requires-Dist: dask[dataframe]<2025,>=2023.5.0
Requires-Dist: pandera==0.24.0
Requires-Dist: shapely==2.1.1
Requires-Dist: geocube>=0.7.1
Requires-Dist: pandas==2.2.3
Requires-Dist: odc-geo==0.4.10
Requires-Dist: pydantic>=1.10.13
Requires-Dist: rio-cogeo==5.4.1
Requires-Dist: matplotlib==3.10.3
Requires-Dist: contextily==1.6.2
Requires-Dist: flox==0.10.3
Requires-Dist: xskillscore==0.0.26
Requires-Dist: pyogrio<=0.11.0,>=0.7.2
Requires-Dist: pystac-client==0.8.6
Requires-Dist: s3fs<=2025.5.0
Requires-Dist: numba==0.61.2
Requires-Dist: pyarrow==20.0.0
Provides-Extra: dev
Requires-Dist: flake8==6.0.0; extra == "dev"
Requires-Dist: flake8-black==0.3.6; extra == "dev"
Requires-Dist: pytest==7.2.2; extra == "dev"
Requires-Dist: pytest-benchmark==4.0.0; extra == "dev"
Requires-Dist: pytest-cov==4.1.0; extra == "dev"
Requires-Dist: pytest-cases==3.6.14; extra == "dev"
Requires-Dist: allure-pytest==2.13.2; extra == "dev"
Requires-Dist: pytest-memray==1.7.0; extra == "dev"
Requires-Dist: pytest-monitor==1.6.6; extra == "dev"
Requires-Dist: boto3==1.26.164; extra == "dev"
Requires-Dist: sqlalchemy==2.0.17; extra == "dev"
Requires-Dist: colorama==0.4.6; extra == "dev"
Requires-Dist: deepdiff==6.7.1; extra == "dev"
Requires-Dist: sphinx==6.2.1; extra == "dev"
Requires-Dist: sphinx-rtd-theme==1.2.2; extra == "dev"
Requires-Dist: myst_parser==2.0.0; extra == "dev"
Requires-Dist: nbsphinx==0.9.2; extra == "dev"
Requires-Dist: pypandoc==1.12; extra == "dev"
Requires-Dist: jupyter==1.0.0; extra == "dev"
Requires-Dist: nox==2023.04.22; extra == "dev"
Requires-Dist: pre-commit==3.3.3; extra == "dev"
Requires-Dist: build==0.10.0; extra == "dev"
Requires-Dist: twine==3.4.2; extra == "dev"
Provides-Extra: linting
Requires-Dist: flake8==6.0.0; extra == "linting"
Requires-Dist: flake8-black==0.3.6; extra == "linting"
Provides-Extra: testing
Requires-Dist: pytest==7.2.2; extra == "testing"
Requires-Dist: pytest-benchmark==4.0.0; extra == "testing"
Requires-Dist: pytest-cov==4.1.0; extra == "testing"
Requires-Dist: pytest-cases==3.6.14; extra == "testing"
Requires-Dist: allure-pytest==2.13.2; extra == "testing"
Requires-Dist: pytest-memray==1.4.1; extra == "testing"
Requires-Dist: pytest-monitor==1.6.6; extra == "testing"
Requires-Dist: boto3==1.26.164; extra == "testing"
Requires-Dist: sqlalchemy==2.0.17; extra == "testing"
Requires-Dist: colorama==0.4.6; extra == "testing"
Requires-Dist: deepdiff==6.7.1; extra == "testing"
Provides-Extra: docs
Requires-Dist: sphinx==6.2.1; extra == "docs"
Requires-Dist: sphinx-rtd-theme==1.2.2; extra == "docs"
Requires-Dist: myst_parser==2.0.0; extra == "docs"
Requires-Dist: nbsphinx==0.9.2; extra == "docs"
Requires-Dist: pypandoc==1.12; extra == "docs"
Requires-Dist: jupyter==1.0.0; extra == "docs"
Provides-Extra: ci-cd-automation
Requires-Dist: nox==2023.04.22; extra == "ci-cd-automation"
Requires-Dist: pre-commit==3.3.3; extra == "ci-cd-automation"
Provides-Extra: other
Requires-Dist: build==0.10.0; extra == "other"
Requires-Dist: twine==3.4.2; extra == "other"
Dynamic: license-file
